mlk/__init__.py
mlk/conf.py
mlk/checker/__init__.py
mlk/checker/checkutils.py
mlk/lib/__init__.py
mlk/lib/core.py
mlk/log/__init__.py
mlk/log/keraslogutils.py
mlk/test/__init__.py
mlk/test/test_conf.py
mlk/viz/Numpy.py
mlk/viz/NumpyBase.py
mlk/viz/Seaborn.py
mlk/viz/Stats.py
mlk/viz/__init__.py
mlk/viz/matplotutils.py
mlk/viz/pandas.py
mlk-1.0.3.dist-info/LICENSE
mlk-1.0.3.dist-info/METADATA
mlk-1.0.3.dist-info/WHEEL
mlk-1.0.3.dist-info/top_level.txt
mlk-1.0.3.dist-info/RECORD
