Metadata-Version: 2.1
Name: mlk
Version: 1.0.3
Summary: ML Kit
Home-page: https://github.com/pypa/mlk
Author: Will Nguyen
Author-email: will.ng.nguyen@gmail.com
License: UNKNOWN
Platform: UNKNOWN
Classifier: Programming Language :: Python :: 3
Classifier: License :: OSI Approved :: MIT License
Classifier: Operating System :: OS Independent
Requires-Dist: aiohttp
Requires-Dist: slack-sdk
Requires-Dist: redis
Requires-Dist: requests
Requires-Dist: openpyxl
Requires-Dist: brotli
Requires-Dist: Faker
Requires-Dist: keras
Requires-Dist: seaborn
Requires-Dist: scikit-learn
Requires-Dist: scikit-image
Requires-Dist: pandas
Requires-Dist: matplotlib
Requires-Dist: opencv-python
Requires-Dist: tabulate
Requires-Dist: Pillow
Requires-Dist: texttable
Requires-Dist: wordcloud
Requires-Dist: nltk
Requires-Dist: imutils
Requires-Dist: tensorflow (==2.3.2)
Requires-Dist: numpy (==1.18.5)
Requires-Dist: decorator
